orderable/__init__.py
orderable/admin.py
orderable/managers.py
orderable/models.py
orderable/querysets.py
orderable/static/admin/img/drag_handle.gif
orderable/templates/admin/orderable_change_list.html
orderable/templates/admin/edit_inline/orderable_tabular.html
orderable/tests/__init__.py
orderable/tests/models.py
orderable/tests/run.py
orderable/tests/test_admin.py
orderable/tests/test_manager.py
orderable/tests/test_models.py
orderable/tests/test_querysets.py
django_orderable-6.1.2.dist-info/LICENSE
django_orderable-6.1.2.dist-info/METADATA
django_orderable-6.1.2.dist-info/WHEEL
django_orderable-6.1.2.dist-info/top_level.txt
django_orderable-6.1.2.dist-info/RECORD
